README.md
setup.py
nflscraPy/__init__.py
nflscraPy/expected_points.py
nflscraPy/five_thirty_eight.py
nflscraPy/metadata.py
nflscraPy/roster.py
nflscraPy/scoring.py
nflscraPy/season.py
nflscraPy/snap_counts.py
nflscraPy/splits.py
nflscraPy/stats.py
nflscraPy/teams.py
nflscraPy.egg-info/PKG-INFO
nflscraPy.egg-info/SOURCES.txt
nflscraPy.egg-info/dependency_links.txt
nflscraPy.egg-info/requires.txt
nflscraPy.egg-info/top_level.txt