Metadata-Version: 1.1
Name: nflscraPy
Version: 0.1.3
Summary: Datasets and Scraping Functions for NFL Data
Home-page: https://github.com/blnkpagelabs/nflscraPy
Author: Tyler Durden
Author-email: blankpagelabs@gmail.com
License: MIT License
Keywords: python,scraper,NFL Data,Pro Football Reference,Sports Reference,fiveThirtyEight
Platform: UNKNOWN
Classifier: Development Status :: 3 - Alpha
Classifier: Programming Language :: Python :: 3
Classifier: Operating System :: OS Independent
